{"date": "2026-05-15", "readings": [{"time": "01:31", "total_kw": 2098.0, "online": 26, "buildings": {"grimes": 34.7, "davis": 189.0, "etch": 12.1, "hmm": 487.4, "hesse": 119.8, "mclaughlin": 101.7, "stanley": 34.7, "latimer": 6.0, "birge": 3.0, "hilde": 71.6, "wheeler": 29.3, "dwinelle": 42.1, "moses": 11.9, "stephens": 20.4, "wurster": 1.9, "giannini": 32.4, "morgan": 13.0, "rsf": 111.0, "chavez": 39.0, "sproul": 76.6, "doe": 27.5, "moffitt": 115.0, "northgate": 7.0, "donner": 26.0, "bww": 447.9, "mulford": 37.0}}]}