{
  "generated_at": "2026-04-13 06:35:43",
  "period": {
    "start": "2026-04-10",
    "end": "2026-04-13",
    "days": 4,
    "total_readings": 66
  },
  "campus_summary": {
    "avg_kw": 1737.1,
    "peak_kw": 2147.2,
    "min_kw": 1597.8,
    "total_kwh": 166762.0,
    "total_cost": 25014.3,
    "total_co2_kg": 35020.0,
    "total_co2_tons": 35.02,
    "trees_equivalent": 1614
  },
  "daily_breakdown": [
    {
      "date": "2026-04-10",
      "day": "Friday",
      "avg_kw": 2064.8,
      "peak_kw": 2147.2,
      "peak_time": "22:03",
      "min_kw": 2018.6,
      "readings_count": 6,
      "avg_online": 26,
      "est_kwh": 49555.0,
      "est_cost": 7433.25,
      "est_co2_kg": 10406.5
    },
    {
      "date": "2026-04-11",
      "day": "Saturday",
      "avg_kw": 1704.0,
      "peak_kw": 1808.7,
      "peak_time": "22:22",
      "min_kw": 1604.6,
      "readings_count": 30,
      "avg_online": 26,
      "est_kwh": 40896.0,
      "est_cost": 6134.4,
      "est_co2_kg": 8588.2
    },
    {
      "date": "2026-04-12",
      "day": "Sunday",
      "avg_kw": 1703.1,
      "peak_kw": 1900.9,
      "peak_time": "19:27",
      "min_kw": 1597.8,
      "readings_count": 27,
      "avg_online": 26,
      "est_kwh": 40874.0,
      "est_cost": 6131.1,
      "est_co2_kg": 8583.5
    },
    {
      "date": "2026-04-13",
      "day": "Monday",
      "avg_kw": 1717.5,
      "peak_kw": 1773.3,
      "peak_time": "01:30",
      "min_kw": 1688.8,
      "readings_count": 3,
      "avg_online": 26,
      "est_kwh": 41220.0,
      "est_cost": 6183.0,
      "est_co2_kg": 8656.2
    }
  ],
  "building_rankings": {
    "hmm": {
      "avg_kw": 426.2,
      "peak_kw": 469.8,
      "min_kw": 411.1,
      "readings": 66,
      "est_weekly_kwh": 71606.0,
      "est_weekly_cost": 10740.93,
      "est_weekly_co2_kg": 15037.3
    },
    "bww": {
      "avg_kw": 379.3,
      "peak_kw": 408.2,
      "min_kw": 355.0,
      "readings": 66,
      "est_weekly_kwh": 63727.0,
      "est_weekly_cost": 9559.01,
      "est_weekly_co2_kg": 13382.6
    },
    "davis": {
      "avg_kw": 176.9,
      "peak_kw": 255.0,
      "min_kw": 153.0,
      "readings": 66,
      "est_weekly_kwh": 29723.0,
      "est_weekly_cost": 4458.49,
      "est_weekly_co2_kg": 6241.9
    },
    "moffitt": {
      "avg_kw": 105.1,
      "peak_kw": 137.0,
      "min_kw": 90.0,
      "readings": 66,
      "est_weekly_kwh": 17653.0,
      "est_weekly_cost": 2647.91,
      "est_weekly_co2_kg": 3707.1
    },
    "hesse": {
      "avg_kw": 98.7,
      "peak_kw": 108.1,
      "min_kw": 94.4,
      "readings": 66,
      "est_weekly_kwh": 16581.0,
      "est_weekly_cost": 2487.09,
      "est_weekly_co2_kg": 3481.9
    },
    "rsf": {
      "avg_kw": 97.9,
      "peak_kw": 150.0,
      "min_kw": 25.0,
      "readings": 66,
      "est_weekly_kwh": 16444.0,
      "est_weekly_cost": 2466.55,
      "est_weekly_co2_kg": 3453.2
    },
    "hilde": {
      "avg_kw": 73.0,
      "peak_kw": 94.2,
      "min_kw": 59.1,
      "readings": 66,
      "est_weekly_kwh": 12271.0,
      "est_weekly_cost": 1840.67,
      "est_weekly_co2_kg": 2576.9
    },
    "sproul": {
      "avg_kw": 72.7,
      "peak_kw": 95.7,
      "min_kw": 64.0,
      "readings": 66,
      "est_weekly_kwh": 12222.0,
      "est_weekly_cost": 1833.26,
      "est_weekly_co2_kg": 2566.6
    },
    "chavez": {
      "avg_kw": 43.0,
      "peak_kw": 139.0,
      "min_kw": 21.0,
      "readings": 66,
      "est_weekly_kwh": 7221.0,
      "est_weekly_cost": 1083.22,
      "est_weekly_co2_kg": 1516.5
    },
    "mulford": {
      "avg_kw": 36.6,
      "peak_kw": 65.0,
      "min_kw": 30.0,
      "readings": 66,
      "est_weekly_kwh": 6152.0,
      "est_weekly_cost": 922.85,
      "est_weekly_co2_kg": 1292.0
    },
    "dwinelle": {
      "avg_kw": 30.5,
      "peak_kw": 51.2,
      "min_kw": 26.6,
      "readings": 66,
      "est_weekly_kwh": 5118.0,
      "est_weekly_cost": 767.65,
      "est_weekly_co2_kg": 1074.7
    },
    "mclaughlin": {
      "avg_kw": 28.3,
      "peak_kw": 71.3,
      "min_kw": 14.9,
      "readings": 66,
      "est_weekly_kwh": 4755.0,
      "est_weekly_cost": 713.24,
      "est_weekly_co2_kg": 998.5
    },
    "donner": {
      "avg_kw": 23.2,
      "peak_kw": 41.0,
      "min_kw": 20.0,
      "readings": 66,
      "est_weekly_kwh": 3889.0,
      "est_weekly_cost": 583.42,
      "est_weekly_co2_kg": 816.8
    },
    "doe": {
      "avg_kw": 19.0,
      "peak_kw": 28.0,
      "min_kw": 5.4,
      "readings": 66,
      "est_weekly_kwh": 3198.0,
      "est_weekly_cost": 479.72,
      "est_weekly_co2_kg": 671.6
    },
    "stephens": {
      "avg_kw": 16.4,
      "peak_kw": 27.7,
      "min_kw": 8.4,
      "readings": 66,
      "est_weekly_kwh": 2749.0,
      "est_weekly_cost": 412.33,
      "est_weekly_co2_kg": 577.3
    },
    "giannini": {
      "avg_kw": 16.1,
      "peak_kw": 38.7,
      "min_kw": 10.5,
      "readings": 66,
      "est_weekly_kwh": 2696.0,
      "est_weekly_cost": 404.46,
      "est_weekly_co2_kg": 566.2
    },
    "grimes": {
      "avg_kw": 15.8,
      "peak_kw": 85.8,
      "min_kw": 8.6,
      "readings": 66,
      "est_weekly_kwh": 2647.0,
      "est_weekly_cost": 396.98,
      "est_weekly_co2_kg": 555.8
    },
    "stanley": {
      "avg_kw": 15.8,
      "peak_kw": 85.8,
      "min_kw": 8.6,
      "readings": 66,
      "est_weekly_kwh": 2647.0,
      "est_weekly_cost": 396.98,
      "est_weekly_co2_kg": 555.8
    },
    "wheeler": {
      "avg_kw": 14.7,
      "peak_kw": 35.6,
      "min_kw": 10.4,
      "readings": 66,
      "est_weekly_kwh": 2465.0,
      "est_weekly_cost": 369.75,
      "est_weekly_co2_kg": 517.7
    },
    "moses": {
      "avg_kw": 12.4,
      "peak_kw": 23.6,
      "min_kw": 9.4,
      "readings": 66,
      "est_weekly_kwh": 2091.0,
      "est_weekly_cost": 313.63,
      "est_weekly_co2_kg": 439.1
    },
    "etch": {
      "avg_kw": 12.1,
      "peak_kw": 12.1,
      "min_kw": 12.1,
      "readings": 66,
      "est_weekly_kwh": 2033.0,
      "est_weekly_cost": 304.92,
      "est_weekly_co2_kg": 426.9
    },
    "morgan": {
      "avg_kw": 6.7,
      "peak_kw": 10.3,
      "min_kw": 6.1,
      "readings": 66,
      "est_weekly_kwh": 1119.0,
      "est_weekly_cost": 167.81,
      "est_weekly_co2_kg": 234.9
    },
    "latimer": {
      "avg_kw": 6.0,
      "peak_kw": 14.0,
      "min_kw": 5.0,
      "readings": 66,
      "est_weekly_kwh": 1011.0,
      "est_weekly_cost": 151.58,
      "est_weekly_co2_kg": 212.2
    },
    "northgate": {
      "avg_kw": 5.7,
      "peak_kw": 7.3,
      "min_kw": 4.9,
      "readings": 66,
      "est_weekly_kwh": 964.0,
      "est_weekly_cost": 144.67,
      "est_weekly_co2_kg": 202.5
    },
    "wurster": {
      "avg_kw": 3.1,
      "peak_kw": 3.1,
      "min_kw": 3.1,
      "readings": 66,
      "est_weekly_kwh": 521.0,
      "est_weekly_cost": 78.12,
      "est_weekly_co2_kg": 109.4
    },
    "birge": {
      "avg_kw": 1.9,
      "peak_kw": 5.3,
      "min_kw": 1.5,
      "readings": 66,
      "est_weekly_kwh": 324.0,
      "est_weekly_cost": 48.61,
      "est_weekly_co2_kg": 68.0
    }
  }
}