{
  "generated_at": "2026-04-18 15:23:28",
  "period": {
    "start": "2026-04-12",
    "end": "2026-04-18",
    "days": 7,
    "total_readings": 131
  },
  "campus_summary": {
    "avg_kw": 1851.0,
    "peak_kw": 2372.5,
    "min_kw": 1534.3,
    "total_kwh": 310968.0,
    "total_cost": 46645.2,
    "total_co2_kg": 65303.3,
    "total_co2_tons": 65.3,
    "trees_equivalent": 3009
  },
  "daily_breakdown": [
    {
      "date": "2026-04-12",
      "day": "Sunday",
      "avg_kw": 1703.1,
      "peak_kw": 1900.9,
      "peak_time": "19:27",
      "min_kw": 1597.8,
      "readings_count": 27,
      "avg_online": 26,
      "est_kwh": 40874.0,
      "est_cost": 6131.1,
      "est_co2_kg": 8583.5
    },
    {
      "date": "2026-04-13",
      "day": "Monday",
      "avg_kw": 1948.5,
      "peak_kw": 2322.6,
      "peak_time": "21:32",
      "min_kw": 1619.6,
      "readings_count": 17,
      "avg_online": 26,
      "est_kwh": 46764.0,
      "est_cost": 7014.6,
      "est_co2_kg": 9820.4
    },
    {
      "date": "2026-04-14",
      "day": "Tuesday",
      "avg_kw": 1911.8,
      "peak_kw": 2296.7,
      "peak_time": "20:42",
      "min_kw": 1595.0,
      "readings_count": 18,
      "avg_online": 26,
      "est_kwh": 45883.0,
      "est_cost": 6882.45,
      "est_co2_kg": 9635.4
    },
    {
      "date": "2026-04-15",
      "day": "Wednesday",
      "avg_kw": 1920.2,
      "peak_kw": 2301.4,
      "peak_time": "19:00",
      "min_kw": 1578.8,
      "readings_count": 17,
      "avg_online": 26,
      "est_kwh": 46085.0,
      "est_cost": 6912.75,
      "est_co2_kg": 9677.9
    },
    {
      "date": "2026-04-16",
      "day": "Thursday",
      "avg_kw": 1959.9,
      "peak_kw": 2372.5,
      "peak_time": "19:37",
      "min_kw": 1613.9,
      "readings_count": 17,
      "avg_online": 26,
      "est_kwh": 47038.0,
      "est_cost": 7055.7,
      "est_co2_kg": 9878.0
    },
    {
      "date": "2026-04-17",
      "day": "Friday",
      "avg_kw": 1908.1,
      "peak_kw": 2368.3,
      "peak_time": "21:08",
      "min_kw": 1617.8,
      "readings_count": 20,
      "avg_online": 26,
      "est_kwh": 45794.0,
      "est_cost": 6869.1,
      "est_co2_kg": 9616.7
    },
    {
      "date": "2026-04-18",
      "day": "Saturday",
      "avg_kw": 1655.8,
      "peak_kw": 2028.1,
      "peak_time": "00:01",
      "min_kw": 1534.3,
      "readings_count": 15,
      "avg_online": 26,
      "est_kwh": 39739.0,
      "est_cost": 5960.85,
      "est_co2_kg": 8345.2
    }
  ],
  "building_rankings": {
    "hmm": {
      "avg_kw": 434.6,
      "peak_kw": 523.6,
      "min_kw": 404.8,
      "readings": 131,
      "est_weekly_kwh": 73013.0,
      "est_weekly_cost": 10952.02,
      "est_weekly_co2_kg": 15332.8
    },
    "bww": {
      "avg_kw": 371.8,
      "peak_kw": 435.7,
      "min_kw": 334.7,
      "readings": 131,
      "est_weekly_kwh": 62468.0,
      "est_weekly_cost": 9370.19,
      "est_weekly_co2_kg": 13118.3
    },
    "davis": {
      "avg_kw": 191.3,
      "peak_kw": 279.0,
      "min_kw": 143.0,
      "readings": 131,
      "est_weekly_kwh": 32144.0,
      "est_weekly_cost": 4821.66,
      "est_weekly_co2_kg": 6750.3
    },
    "moffitt": {
      "avg_kw": 113.2,
      "peak_kw": 160.0,
      "min_kw": 86.0,
      "readings": 131,
      "est_weekly_kwh": 19013.0,
      "est_weekly_cost": 2852.02,
      "est_weekly_co2_kg": 3992.8
    },
    "hesse": {
      "avg_kw": 105.5,
      "peak_kw": 127.7,
      "min_kw": 94.5,
      "readings": 131,
      "est_weekly_kwh": 17718.0,
      "est_weekly_cost": 2657.75,
      "est_weekly_co2_kg": 3720.9
    },
    "rsf": {
      "avg_kw": 87.4,
      "peak_kw": 190.0,
      "min_kw": 2.0,
      "readings": 131,
      "est_weekly_kwh": 14690.0,
      "est_weekly_cost": 2203.56,
      "est_weekly_co2_kg": 3085.0
    },
    "sproul": {
      "avg_kw": 87.2,
      "peak_kw": 135.3,
      "min_kw": 66.7,
      "readings": 131,
      "est_weekly_kwh": 14653.0,
      "est_weekly_cost": 2197.98,
      "est_weekly_co2_kg": 3077.2
    },
    "hilde": {
      "avg_kw": 73.6,
      "peak_kw": 102.4,
      "min_kw": 54.0,
      "readings": 131,
      "est_weekly_kwh": 12371.0,
      "est_weekly_cost": 1855.72,
      "est_weekly_co2_kg": 2598.0
    },
    "chavez": {
      "avg_kw": 67.1,
      "peak_kw": 158.0,
      "min_kw": 21.0,
      "readings": 131,
      "est_weekly_kwh": 11270.0,
      "est_weekly_cost": 1690.52,
      "est_weekly_co2_kg": 2366.7
    },
    "mulford": {
      "avg_kw": 44.1,
      "peak_kw": 74.0,
      "min_kw": 30.0,
      "readings": 131,
      "est_weekly_kwh": 7409.0,
      "est_weekly_cost": 1111.3,
      "est_weekly_co2_kg": 1555.8
    },
    "dwinelle": {
      "avg_kw": 37.0,
      "peak_kw": 58.8,
      "min_kw": 26.1,
      "readings": 131,
      "est_weekly_kwh": 6208.0,
      "est_weekly_cost": 931.19,
      "est_weekly_co2_kg": 1303.7
    },
    "mclaughlin": {
      "avg_kw": 35.2,
      "peak_kw": 124.8,
      "min_kw": 14.0,
      "readings": 131,
      "est_weekly_kwh": 5921.0,
      "est_weekly_cost": 888.08,
      "est_weekly_co2_kg": 1243.3
    },
    "giannini": {
      "avg_kw": 24.4,
      "peak_kw": 55.4,
      "min_kw": 10.5,
      "readings": 131,
      "est_weekly_kwh": 4106.0,
      "est_weekly_cost": 615.96,
      "est_weekly_co2_kg": 862.3
    },
    "donner": {
      "avg_kw": 23.6,
      "peak_kw": 46.0,
      "min_kw": 20.0,
      "readings": 131,
      "est_weekly_kwh": 3970.0,
      "est_weekly_cost": 595.57,
      "est_weekly_co2_kg": 833.8
    },
    "grimes": {
      "avg_kw": 21.1,
      "peak_kw": 85.8,
      "min_kw": 3.8,
      "readings": 131,
      "est_weekly_kwh": 3551.0,
      "est_weekly_cost": 532.66,
      "est_weekly_co2_kg": 745.7
    },
    "stanley": {
      "avg_kw": 21.1,
      "peak_kw": 85.8,
      "min_kw": 3.8,
      "readings": 131,
      "est_weekly_kwh": 3551.0,
      "est_weekly_cost": 532.66,
      "est_weekly_co2_kg": 745.7
    },
    "wheeler": {
      "avg_kw": 20.6,
      "peak_kw": 38.8,
      "min_kw": 9.7,
      "readings": 131,
      "est_weekly_kwh": 3462.0,
      "est_weekly_cost": 519.29,
      "est_weekly_co2_kg": 727.0
    },
    "stephens": {
      "avg_kw": 19.4,
      "peak_kw": 31.8,
      "min_kw": 8.4,
      "readings": 131,
      "est_weekly_kwh": 3258.0,
      "est_weekly_cost": 488.63,
      "est_weekly_co2_kg": 684.1
    },
    "doe": {
      "avg_kw": 19.4,
      "peak_kw": 29.1,
      "min_kw": 5.4,
      "readings": 131,
      "est_weekly_kwh": 3259.0,
      "est_weekly_cost": 488.86,
      "est_weekly_co2_kg": 684.4
    },
    "moses": {
      "avg_kw": 13.6,
      "peak_kw": 26.0,
      "min_kw": 9.1,
      "readings": 131,
      "est_weekly_kwh": 2289.0,
      "est_weekly_cost": 343.39,
      "est_weekly_co2_kg": 480.8
    },
    "etch": {
      "avg_kw": 12.1,
      "peak_kw": 12.1,
      "min_kw": 12.1,
      "readings": 131,
      "est_weekly_kwh": 2033.0,
      "est_weekly_cost": 304.92,
      "est_weekly_co2_kg": 426.9
    },
    "latimer": {
      "avg_kw": 8.4,
      "peak_kw": 16.0,
      "min_kw": 5.0,
      "readings": 131,
      "est_weekly_kwh": 1413.0,
      "est_weekly_cost": 211.99,
      "est_weekly_co2_kg": 296.8
    },
    "morgan": {
      "avg_kw": 8.1,
      "peak_kw": 23.8,
      "min_kw": 6.1,
      "readings": 131,
      "est_weekly_kwh": 1359.0,
      "est_weekly_cost": 203.81,
      "est_weekly_co2_kg": 285.3
    },
    "northgate": {
      "avg_kw": 6.1,
      "peak_kw": 7.8,
      "min_kw": 4.9,
      "readings": 131,
      "est_weekly_kwh": 1023.0,
      "est_weekly_cost": 153.45,
      "est_weekly_co2_kg": 214.8
    },
    "birge": {
      "avg_kw": 2.4,
      "peak_kw": 7.2,
      "min_kw": 1.5,
      "readings": 131,
      "est_weekly_kwh": 408.0,
      "est_weekly_cost": 61.23,
      "est_weekly_co2_kg": 85.7
    },
    "wurster": {
      "avg_kw": 2.4,
      "peak_kw": 3.1,
      "min_kw": 1.9,
      "readings": 131,
      "est_weekly_kwh": 407.0,
      "est_weekly_cost": 61.06,
      "est_weekly_co2_kg": 85.5
    }
  }
}